odoo/addons/sale_commission_advance/README.rst
odoo/addons/sale_commission_advance/__init__.py
odoo/addons/sale_commission_advance/__manifest__.py
odoo/addons/sale_commission_advance/i18n/es.po
odoo/addons/sale_commission_advance/i18n/it.po
odoo/addons/sale_commission_advance/i18n/pt_BR.po
odoo/addons/sale_commission_advance/i18n/sale_commission_advance.pot
odoo/addons/sale_commission_advance/models/__init__.py
odoo/addons/sale_commission_advance/models/account_move.py
odoo/addons/sale_commission_advance/models/sale_order.py
odoo/addons/sale_commission_advance/readme/CONTRIBUTORS.rst
odoo/addons/sale_commission_advance/readme/DESCRIPTION.rst
odoo/addons/sale_commission_advance/readme/USAGE.rst
odoo/addons/sale_commission_advance/static/description/icon.png
odoo/addons/sale_commission_advance/static/description/index.html
odoo/addons/sale_commission_advance/tests/__init__.py
odoo/addons/sale_commission_advance/tests/test_sale_commission_advance.py
odoo14_addon_sale_commission_advance-14.0.1.0.1.dev14.dist-info/METADATA
odoo14_addon_sale_commission_advance-14.0.1.0.1.dev14.dist-info/WHEEL
odoo14_addon_sale_commission_advance-14.0.1.0.1.dev14.dist-info/top_level.txt
odoo14_addon_sale_commission_advance-14.0.1.0.1.dev14.dist-info/RECORD
